primoEAB/primoEAB.py
primoEAB-1.0.1.dist-info/LICENSE
primoEAB-1.0.1.dist-info/METADATA
primoEAB-1.0.1.dist-info/WHEEL
primoEAB-1.0.1.dist-info/top_level.txt
primoEAB-1.0.1.dist-info/RECORD
