Metadata-Version: 2.1
Name: primoEAB
Version: 1.0.1
Summary: A function that prints prime numbers up to n.
Home-page: UNKNOWN
Author: Elena Arbiol
Author-email: elenaarbiol@yahoo.es
License: GNU GPLv3
Keywords: primo prime
Platform: UNKNOWN
Classifier: Development Status :: 4 - Beta
Classifier: Intended Audience :: Developers
Classifier: Topic :: Utilities
Classifier: License :: OSI Approved :: GNU General Public License v3 (GPLv3)
Classifier: Programming Language :: Python :: 3
Classifier: Operating System :: OS Independent
License-File: LICENSE
